odoo9_addon_purchase_date_planned_manual-9.0.1.0.0.99.dev7-py2.7-nspkg.pth
odoo9_addon_purchase_date_planned_manual-9.0.1.0.0.99.dev7.dist-info/DESCRIPTION.rst
odoo9_addon_purchase_date_planned_manual-9.0.1.0.0.99.dev7.dist-info/METADATA
odoo9_addon_purchase_date_planned_manual-9.0.1.0.0.99.dev7.dist-info/RECORD
odoo9_addon_purchase_date_planned_manual-9.0.1.0.0.99.dev7.dist-info/WHEEL
odoo9_addon_purchase_date_planned_manual-9.0.1.0.0.99.dev7.dist-info/metadata.json
odoo9_addon_purchase_date_planned_manual-9.0.1.0.0.99.dev7.dist-info/namespace_packages.txt
odoo9_addon_purchase_date_planned_manual-9.0.1.0.0.99.dev7.dist-info/top_level.txt
odoo_addons/purchase_date_planned_manual/README.rst
odoo_addons/purchase_date_planned_manual/__init__.py
odoo_addons/purchase_date_planned_manual/__openerp__.py
odoo_addons/purchase_date_planned_manual/i18n/de.po
odoo_addons/purchase_date_planned_manual/i18n/es.po
odoo_addons/purchase_date_planned_manual/i18n/es_MX.po
odoo_addons/purchase_date_planned_manual/i18n/es_PE.po
odoo_addons/purchase_date_planned_manual/i18n/fi.po
odoo_addons/purchase_date_planned_manual/i18n/fr.po
odoo_addons/purchase_date_planned_manual/i18n/fr_FR.po
odoo_addons/purchase_date_planned_manual/i18n/gl.po
odoo_addons/purchase_date_planned_manual/i18n/hr.po
odoo_addons/purchase_date_planned_manual/i18n/it.po
odoo_addons/purchase_date_planned_manual/i18n/nl.po
odoo_addons/purchase_date_planned_manual/i18n/nl_NL.po
odoo_addons/purchase_date_planned_manual/i18n/pt_BR.po
odoo_addons/purchase_date_planned_manual/i18n/pt_PT.po
odoo_addons/purchase_date_planned_manual/i18n/ro.po
odoo_addons/purchase_date_planned_manual/i18n/sk.po
odoo_addons/purchase_date_planned_manual/i18n/sl.po
odoo_addons/purchase_date_planned_manual/i18n/tr_TR.po
odoo_addons/purchase_date_planned_manual/i18n/vi_VN.po
odoo_addons/purchase_date_planned_manual/i18n/zh_CN.po
odoo_addons/purchase_date_planned_manual/models/__init__.py
odoo_addons/purchase_date_planned_manual/models/procurement_order.py
odoo_addons/purchase_date_planned_manual/models/purchase_order.py
odoo_addons/purchase_date_planned_manual/static/description/icon.png
odoo_addons/purchase_date_planned_manual/tests/__init__.py
odoo_addons/purchase_date_planned_manual/tests/test_date_planned_manual.py
odoo_addons/purchase_date_planned_manual/views/purchase_order_view.xml
